subcursor/__init__.py
subcursor/__main__.py
subcursor/cli.py
subcursor/redirect_interpose.c
subcursor/.cursor/subagents/backend/description.txt
subcursor/.cursor/subagents/backend/.cursor/mcp.json
subcursor/.cursor/subagents/backend/.cursor/rules/.cursorrules
subcursor/.cursor/subagents/designer/description.txt
subcursor/.cursor/subagents/designer/.cursor/mcp.json
subcursor/.cursor/subagents/designer/.cursor/rules/.cursorrules
subcursor/.cursor/subagents/frontend/description.txt
subcursor/.cursor/subagents/frontend/.cursor/mcp.json
subcursor/.cursor/subagents/frontend/.cursor/rules/.cursorrules
subcursor-0.1.0.dist-info/METADATA
subcursor-0.1.0.dist-info/WHEEL
subcursor-0.1.0.dist-info/entry_points.txt
subcursor-0.1.0.dist-info/licenses/LICENSE
subcursor-0.1.0.dist-info/RECORD
