Metadata-Version: 2.4
Name: subcursor
Version: 0.1.0
Summary: Specialized AI subagents for Cursor with isolated configurations
Project-URL: Homepage, https://github.com/yoavain/subcursor
Project-URL: Repository, https://github.com/yoavain/subcursor
Project-URL: Documentation, https://github.com/yoavain/subcursor#readme
Author: subcursor contributors
License: MIT
License-File: LICENSE
Keywords: ai,cursor,llm,mcp,subagents
Classifier: Development Status :: 4 - Beta
Classifier: Intended Audience :: Developers
Classifier: License :: OSI Approved :: MIT License
Classifier: Programming Language :: Python :: 3
Classifier: Programming Language :: Python :: 3.11
Classifier: Programming Language :: Python :: 3.12
Classifier: Topic :: Software Development :: Libraries
Requires-Python: >=3.11
Requires-Dist: mcp>=1.0.0
Requires-Dist: pydantic>=2.0.0
